pyramid_iap/__init__.py
pyramid_iap/claims.py
pyramid_iap/policy.py
pyramid_iap-0.1.dist-info/LICENSE.txt
pyramid_iap-0.1.dist-info/METADATA
pyramid_iap-0.1.dist-info/WHEEL
pyramid_iap-0.1.dist-info/top_level.txt
pyramid_iap-0.1.dist-info/zip-safe
pyramid_iap-0.1.dist-info/RECORD
