Metadata-Version: 2.1
Name: pyramid-iap
Version: 0.1
Summary: Google Cloud Identity-Aware Proxy authentication policy for Pyramid
Home-page: https://github.com/lrowe/pyramid_iap
Author: Laurence Rowe
Author-email: laurence@lrowe.co.uk
License: BSD
Keywords: Pyramid JWT IAP authentication security
Platform: UNKNOWN
Classifier: Intended Audience :: Developers
Classifier: License :: OSI Approved :: BSD License
Classifier: Operating System :: OS Independent
Classifier: Programming Language :: Python :: 3
Classifier: Programming Language :: Python :: 3.4
Classifier: Programming Language :: Python :: 3.5
Classifier: Programming Language :: Python :: 3.6
Classifier: Programming Language :: Python :: 3.7
Classifier: Topic :: Software Development :: Libraries :: Python Modules
Requires-Dist: pyramid
Requires-Dist: PyJWT
Requires-Dist: cryptography
Requires-Dist: requests
Requires-Dist: zope.interface
Provides-Extra: tests
Requires-Dist: pytest ; extra == 'tests'
Requires-Dist: pytest-flake8 ; extra == 'tests'
Requires-Dist: requests-mock ; extra == 'tests'
Requires-Dist: WebTest ; extra == 'tests'
